logbless/__init__.py
logbless/app.py
logbless/cli.py
logbless/config.py
logbless/constants.py
logbless/static/log_viewer.css
logbless/static/log_viewer.html
logbless/static/log_viewer.js
logbless-0.1.4.dist-info/METADATA
logbless-0.1.4.dist-info/WHEEL
logbless-0.1.4.dist-info/entry_points.txt
logbless-0.1.4.dist-info/top_level.txt
logbless-0.1.4.dist-info/RECORD
