Metadata-Version: 2.2
Name: logbless
Version: 0.1.4
Summary: Simple logs for any app
Author: kesha1225
Project-URL: Homepage, https://github.com/kesha1225/Logbless
Project-URL: Repository, https://github.com/kesha1225/Logbless
Keywords: logs,logging,log viewer,real-time,monitoring,FastAPI,lightweight
Classifier: Development Status :: 5 - Production/Stable
Classifier: Intended Audience :: Developers
Classifier: Intended Audience :: System Administrators
Classifier: Topic :: Software Development :: Libraries :: Application Frameworks
Classifier: Topic :: Utilities
Classifier: Topic :: System :: Logging
Classifier: Topic :: System :: Monitoring
Classifier: Environment :: Console
Classifier: Environment :: Web Environment
Classifier: Framework :: FastAPI
Classifier: License :: OSI Approved :: MIT License
Classifier: Programming Language :: Python
Classifier: Programming Language :: Python :: 3.12
Classifier: Operating System :: OS Independent
Requires-Python: >=3.12
Requires-Dist: fastapi>=0.115.6
Requires-Dist: pyyaml>=6.0.2
Requires-Dist: uvicorn>=0.34.0
